{
  "data": [
    {
      "campaign_name": "Jídelní_Sety_broad_Video_V1",
      "adset_name": "Broad_30-60_Jídelní_Sety_Video_V1",
      "ad_name": "Jídelní_Sety_V1",
      "impressions": "45",
      "clicks": "2",
      "spend": "5.42",
      "ctr": "4.444444",
      "cpc": "2.71",
      "actions": [
        {
          "action_type": "omni_search",
          "value": "2"
        },
        {
          "action_type": "offsite_conversion.fb_pixel_search",
          "value": "2"
        },
        {
          "action_type": "link_click",
          "value": "1"
        },
        {
          "action_type": "page_engagement",
          "value": "8"
        },
        {
          "action_type": "landing_page_view",
          "value": "1"
        },
        {
          "action_type": "omni_landing_page_view",
          "value": "1"
        },
        {
          "action_type": "onsite_web_view_content",
          "value": "2"
        },
        {
          "action_type": "post_interaction_gross",
          "value": "1"
        },
        {
          "action_type": "onsite_web_app_view_content",
          "value": "2"
        },
        {
          "action_type": "view_content",
          "value": "2"
        },
        {
          "action_type": "onsite_conversion.post_save",
          "value": "1"
        },
        {
          "action_type": "post_engagement",
          "value": "8"
        },
        {
          "action_type": "offsite_search_add_meta_leads",
          "value": "2"
        },
        {
          "action_type": "onsite_conversion.post_net_save",
          "value": "1"
        },
        {
          "action_type": "offsite_content_view_add_meta_leads",
          "value": "2"
        },
        {
          "action_type": "search",
          "value": "2"
        },
        {
          "action_type": "video_view",
          "value": "6"
        },
        {
          "action_type": "omni_view_content",
          "value": "2"
        },
        {
          "action_type": "offsite_conversion.fb_pixel_view_content",
          "value": "2"
        }
      ],
      "date_start": "2026-03-17",
      "date_stop": "2026-03-24"
    },
    {
      "campaign_name": "Jídelní_Sety_broad_Video_V1",
      "adset_name": "Broad_30-60_Jídelní_Sety_Video_V1",
      "ad_name": "Jídelní_Sety_V2",
      "impressions": "60",
      "clicks": "3",
      "spend": "8.53",
      "ctr": "5",
      "cpc": "2.843333",
      "actions": [
        {
          "action_type": "page_engagement",
          "value": "11"
        },
        {
          "action_type": "onsite_web_view_content",
          "value": "1"
        },
        {
          "action_type": "onsite_web_app_view_content",
          "value": "1"
        },
        {
          "action_type": "view_content",
          "value": "1"
        },
        {
          "action_type": "post_engagement",
          "value": "11"
        },
        {
          "action_type": "offsite_content_view_add_meta_leads",
          "value": "1"
        },
        {
          "action_type": "video_view",
          "value": "11"
        },
        {
          "action_type": "omni_view_content",
          "value": "1"
        },
        {
          "action_type": "offsite_conversion.fb_pixel_view_content",
          "value": "1"
        }
      ],
      "date_start": "2026-03-17",
      "date_stop": "2026-03-24"
    },
    {
      "campaign_name": "Jídelní_Sety_broad_Video_V1",
      "adset_name": "Broad_30-60_Jídelní_Sety_Video_V1",
      "ad_name": "Jídelní_Sety_V4",
      "impressions": "389",
      "clicks": "9",
      "spend": "50.2",
      "ctr": "2.313625",
      "cpc": "5.577778",
      "actions": [
        {
          "action_type": "link_click",
          "value": "2"
        },
        {
          "action_type": "page_engagement",
          "value": "53"
        },
        {
          "action_type": "onsite_web_view_content",
          "value": "7"
        },
        {
          "action_type": "post_interaction_gross",
          "value": "1"
        },
        {
          "action_type": "onsite_web_app_view_content",
          "value": "7"
        },
        {
          "action_type": "view_content",
          "value": "7"
        },
        {
          "action_type": "onsite_conversion.post_save",
          "value": "1"
        },
        {
          "action_type": "post_engagement",
          "value": "53"
        },
        {
          "action_type": "onsite_conversion.post_net_save",
          "value": "1"
        },
        {
          "action_type": "offsite_content_view_add_meta_leads",
          "value": "7"
        },
        {
          "action_type": "video_view",
          "value": "50"
        },
        {
          "action_type": "omni_view_content",
          "value": "7"
        },
        {
          "action_type": "offsite_conversion.fb_pixel_view_content",
          "value": "7"
        }
      ],
      "date_start": "2026-03-17",
      "date_stop": "2026-03-24"
    },
    {
      "campaign_name": "Jídelní_Sety_broad_Video_V1",
      "adset_name": "Broad_30-60_Jídelní_Sety_Video_V1",
      "ad_name": "Jídelní_Sety_V3",
      "impressions": "2369",
      "clicks": "41",
      "spend": "289.23",
      "ctr": "1.730688",
      "cpc": "7.05439",
      "actions": [
        {
          "action_type": "link_click",
          "value": "30"
        },
        {
          "action_type": "page_engagement",
          "value": "356"
        },
        {
          "action_type": "landing_page_view",
          "value": "23"
        },
        {
          "action_type": "omni_landing_page_view",
          "value": "23"
        },
        {
          "action_type": "onsite_web_view_content",
          "value": "42"
        },
        {
          "action_type": "onsite_web_app_view_content",
          "value": "42"
        },
        {
          "action_type": "view_content",
          "value": "42"
        },
        {
          "action_type": "post_engagement",
          "value": "356"
        },
        {
          "action_type": "offsite_content_view_add_meta_leads",
          "value": "42"
        },
        {
          "action_type": "video_view",
          "value": "326"
        },
        {
          "action_type": "omni_view_content",
          "value": "42"
        },
        {
          "action_type": "offsite_conversion.fb_pixel_view_content",
          "value": "42"
        }
      ],
      "date_start": "2026-03-17",
      "date_stop": "2026-03-24"
    },
    {
      "campaign_name": "Jídelní_Židle+kresilka_broad_Video_V1",
      "adset_name": "Broad_30-60_Jídelní_židle_Video_V1",
      "ad_name": "Jídelní_Židle_V1",
      "impressions": "7086",
      "clicks": "189",
      "spend": "871.4",
      "ctr": "2.667231",
      "cpc": "4.610582",
      "actions": [
        {
          "action_type": "web_in_store_purchase",
          "value": "1"
        },
        {
          "action_type": "omni_search",
          "value": "4"
        },
        {
          "action_type": "offsite_conversion.fb_pixel_search",
          "value": "4"
        },
        {
          "action_type": "omni_purchase",
          "value": "1"
        },
        {
          "action_type": "link_click",
          "value": "122"
        },
        {
          "action_type": "omni_add_to_cart",
          "value": "6"
        },
        {
          "action_type": "omni_initiated_checkout",
          "value": "4"
        },
        {
          "action_type": "page_engagement",
          "value": "1011"
        },
        {
          "action_type": "purchase",
          "value": "1"
        },
        {
          "action_type": "landing_page_view",
          "value": "95"
        },
        {
          "action_type": "add_to_cart",
          "value": "6"
        },
        {
          "action_type": "omni_landing_page_view",
          "value": "95"
        },
        {
          "action_type": "onsite_web_view_content",
          "value": "237"
        },
        {
          "action_type": "onsite_web_add_to_cart",
          "value": "6"
        },
        {
          "action_type": "offsite_conversion.fb_pixel_add_payment_info",
          "value": "1"
        },
        {
          "action_type": "onsite_web_app_purchase",
          "value": "1"
        },
        {
          "action_type": "like",
          "value": "2"
        },
        {
          "action_type": "post_interaction_gross",
          "value": "9"
        },
        {
          "action_type": "offsite_conversion.fb_pixel_purchase",
          "value": "1"
        },
        {
          "action_type": "onsite_web_app_view_content",
          "value": "237"
        },
        {
          "action_type": "view_content",
          "value": "237"
        },
        {
          "action_type": "onsite_conversion.post_save",
          "value": "2"
        },
        {
          "action_type": "web_app_in_store_purchase",
          "value": "1"
        },
        {
          "action_type": "onsite_web_app_add_to_cart",
          "value": "6"
        },
        {
          "action_type": "post_engagement",
          "value": "1009"
        },
        {
          "action_type": "onsite_conversion.post_unlike",
          "value": "1"
        },
        {
          "action_type": "offsite_search_add_meta_leads",
          "value": "4"
        },
        {
          "action_type": "onsite_conversion.post_net_like",
          "value": "6"
        },
        {
          "action_type": "onsite_web_initiate_checkout",
          "value": "4"
        },
        {
          "action_type": "onsite_conversion.post_net_save",
          "value": "2"
        },
        {
          "action_type": "offsite_content_view_add_meta_leads",
          "value": "237"
        },
        {
          "action_type": "onsite_web_purchase",
          "value": "1"
        },
        {
          "action_type": "add_payment_info",
          "value": "1"
        },
        {
          "action_type": "search",
          "value": "4"
        },
        {
          "action_type": "video_view",
          "value": "878"
        },
        {
          "action_type": "omni_view_content",
          "value": "237"
        },
        {
          "action_type": "offsite_conversion.fb_pixel_view_content",
          "value": "237"
        },
        {
          "action_type": "offsite_conversion.fb_pixel_add_to_cart",
          "value": "6"
        },
        {
          "action_type": "post_reaction",
          "value": "7"
        },
        {
          "action_type": "offsite_conversion.fb_pixel_initiate_checkout",
          "value": "4"
        },
        {
          "action_type": "initiate_checkout",
          "value": "4"
        }
      ],
      "date_start": "2026-03-17",
      "date_stop": "2026-03-24"
    },
    {
      "campaign_name": "Jídelní_Židle+kresilka_broad_Video_V1",
      "adset_name": "Broad_30-60_Jídelní_židle_Video_V1",
      "ad_name": "Jídelní_Židle_V2",
      "impressions": "292",
      "clicks": "5",
      "spend": "41.82",
      "ctr": "1.712329",
      "cpc": "8.364",
      "actions": [
        {
          "action_type": "link_click",
          "value": "1"
        },
        {
          "action_type": "page_engagement",
          "value": "54"
        },
        {
          "action_type": "onsite_web_view_content",
          "value": "8"
        },
        {
          "action_type": "onsite_web_app_view_content",
          "value": "8"
        },
        {
          "action_type": "view_content",
          "value": "8"
        },
        {
          "action_type": "post_engagement",
          "value": "54"
        },
        {
          "action_type": "offsite_content_view_add_meta_leads",
          "value": "8"
        },
        {
          "action_type": "video_view",
          "value": "53"
        },
        {
          "action_type": "omni_view_content",
          "value": "8"
        },
        {
          "action_type": "offsite_conversion.fb_pixel_view_content",
          "value": "8"
        }
      ],
      "date_start": "2026-03-17",
      "date_stop": "2026-03-24"
    },
    {
      "campaign_name": "Jídelní_Židle+kresilka_broad_Video_V1",
      "adset_name": "Broad_30-60_Jídelní_židle_Video_V1",
      "ad_name": "Jídelní_Židle_V3",
      "impressions": "2648",
      "clicks": "68",
      "spend": "363.91",
      "ctr": "2.567976",
      "cpc": "5.351618",
      "actions": [
        {
          "action_type": "link_click",
          "value": "42"
        },
        {
          "action_type": "omni_add_to_cart",
          "value": "1"
        },
        {
          "action_type": "omni_initiated_checkout",
          "value": "1"
        },
        {
          "action_type": "page_engagement",
          "value": "692"
        },
        {
          "action_type": "landing_page_view",
          "value": "36"
        },
        {
          "action_type": "add_to_cart",
          "value": "1"
        },
        {
          "action_type": "omni_landing_page_view",
          "value": "36"
        },
        {
          "action_type": "onsite_web_view_content",
          "value": "89"
        },
        {
          "action_type": "onsite_web_add_to_cart",
          "value": "1"
        },
        {
          "action_type": "like",
          "value": "1"
        },
        {
          "action_type": "post_interaction_gross",
          "value": "4"
        },
        {
          "action_type": "onsite_web_app_view_content",
          "value": "89"
        },
        {
          "action_type": "view_content",
          "value": "89"
        },
        {
          "action_type": "onsite_conversion.post_save",
          "value": "1"
        },
        {
          "action_type": "onsite_web_app_add_to_cart",
          "value": "1"
        },
        {
          "action_type": "post_engagement",
          "value": "691"
        },
        {
          "action_type": "onsite_conversion.post_net_like",
          "value": "3"
        },
        {
          "action_type": "onsite_web_initiate_checkout",
          "value": "1"
        },
        {
          "action_type": "onsite_conversion.post_net_save",
          "value": "1"
        },
        {
          "action_type": "offsite_content_view_add_meta_leads",
          "value": "89"
        },
        {
          "action_type": "video_view",
          "value": "645"
        },
        {
          "action_type": "omni_view_content",
          "value": "89"
        },
        {
          "action_type": "offsite_conversion.fb_pixel_view_content",
          "value": "89"
        },
        {
          "action_type": "offsite_conversion.fb_pixel_add_to_cart",
          "value": "1"
        },
        {
          "action_type": "post_reaction",
          "value": "3"
        },
        {
          "action_type": "offsite_conversion.fb_pixel_initiate_checkout",
          "value": "1"
        },
        {
          "action_type": "initiate_checkout",
          "value": "1"
        }
      ],
      "date_start": "2026-03-17",
      "date_stop": "2026-03-24"
    },
    {
      "campaign_name": "Jídelní_Židle+kresilka_broad_Video_V1",
      "adset_name": "Broad_30-60_Jídelní_kresilka_Video_V1",
      "ad_name": "Jídelní_Křesílka_V1",
      "impressions": "1118",
      "clicks": "25",
      "spend": "176.46",
      "ctr": "2.236136",
      "cpc": "7.0584",
      "actions": [
        {
          "action_type": "link_click",
          "value": "15"
        },
        {
          "action_type": "page_engagement",
          "value": "225"
        },
        {
          "action_type": "landing_page_view",
          "value": "14"
        },
        {
          "action_type": "omni_landing_page_view",
          "value": "14"
        },
        {
          "action_type": "onsite_web_view_content",
          "value": "11"
        },
        {
          "action_type": "post_interaction_gross",
          "value": "2"
        },
        {
          "action_type": "onsite_web_app_view_content",
          "value": "11"
        },
        {
          "action_type": "view_content",
          "value": "11"
        },
        {
          "action_type": "onsite_conversion.post_save",
          "value": "1"
        },
        {
          "action_type": "post_engagement",
          "value": "225"
        },
        {
          "action_type": "onsite_conversion.post_net_like",
          "value": "1"
        },
        {
          "action_type": "onsite_conversion.post_net_save",
          "value": "1"
        },
        {
          "action_type": "offsite_content_view_add_meta_leads",
          "value": "11"
        },
        {
          "action_type": "video_view",
          "value": "208"
        },
        {
          "action_type": "omni_view_content",
          "value": "11"
        },
        {
          "action_type": "offsite_conversion.fb_pixel_view_content",
          "value": "11"
        },
        {
          "action_type": "post_reaction",
          "value": "1"
        }
      ],
      "date_start": "2026-03-17",
      "date_stop": "2026-03-24"
    },
    {
      "campaign_name": "Jídelní_Židle+kresilka_broad_Video_V1",
      "adset_name": "Broad_30-60_Jídelní_kresilka_Video_V1",
      "ad_name": "Jídelní_Křesílka_V2",
      "impressions": "9416",
      "clicks": "339",
      "spend": "1077.43",
      "ctr": "3.600255",
      "cpc": "3.17826",
      "actions": [
        {
          "action_type": "web_in_store_purchase",
          "value": "1"
        },
        {
          "action_type": "omni_search",
          "value": "3"
        },
        {
          "action_type": "offsite_conversion.fb_pixel_search",
          "value": "3"
        },
        {
          "action_type": "omni_purchase",
          "value": "1"
        },
        {
          "action_type": "link_click",
          "value": "181"
        },
        {
          "action_type": "omni_add_to_cart",
          "value": "9"
        },
        {
          "action_type": "omni_initiated_checkout",
          "value": "6"
        },
        {
          "action_type": "page_engagement",
          "value": "1876"
        },
        {
          "action_type": "purchase",
          "value": "1"
        },
        {
          "action_type": "landing_page_view",
          "value": "201"
        },
        {
          "action_type": "add_to_cart",
          "value": "9"
        },
        {
          "action_type": "omni_landing_page_view",
          "value": "201"
        },
        {
          "action_type": "onsite_web_view_content",
          "value": "240"
        },
        {
          "action_type": "onsite_web_add_to_cart",
          "value": "9"
        },
        {
          "action_type": "offsite_conversion.fb_pixel_add_payment_info",
          "value": "1"
        },
        {
          "action_type": "onsite_web_app_purchase",
          "value": "1"
        },
        {
          "action_type": "like",
          "value": "5"
        },
        {
          "action_type": "post_interaction_gross",
          "value": "14"
        },
        {
          "action_type": "offsite_conversion.fb_pixel_purchase",
          "value": "1"
        },
        {
          "action_type": "onsite_web_app_view_content",
          "value": "240"
        },
        {
          "action_type": "post",
          "value": "1"
        },
        {
          "action_type": "view_content",
          "value": "240"
        },
        {
          "action_type": "onsite_conversion.post_save",
          "value": "4"
        },
        {
          "action_type": "web_app_in_store_purchase",
          "value": "1"
        },
        {
          "action_type": "onsite_web_app_add_to_cart",
          "value": "9"
        },
        {
          "action_type": "post_engagement",
          "value": "1871"
        },
        {
          "action_type": "offsite_search_add_meta_leads",
          "value": "3"
        },
        {
          "action_type": "onsite_conversion.post_net_like",
          "value": "9"
        },
        {
          "action_type": "onsite_web_initiate_checkout",
          "value": "6"
        },
        {
          "action_type": "onsite_conversion.post_net_save",
          "value": "4"
        },
        {
          "action_type": "offsite_content_view_add_meta_leads",
          "value": "240"
        },
        {
          "action_type": "onsite_web_purchase",
          "value": "1"
        },
        {
          "action_type": "add_payment_info",
          "value": "1"
        },
        {
          "action_type": "search",
          "value": "3"
        },
        {
          "action_type": "video_view",
          "value": "1676"
        },
        {
          "action_type": "omni_view_content",
          "value": "240"
        },
        {
          "action_type": "offsite_conversion.fb_pixel_view_content",
          "value": "240"
        },
        {
          "action_type": "offsite_conversion.fb_pixel_add_to_cart",
          "value": "9"
        },
        {
          "action_type": "post_reaction",
          "value": "9"
        },
        {
          "action_type": "offsite_conversion.fb_pixel_initiate_checkout",
          "value": "6"
        },
        {
          "action_type": "initiate_checkout",
          "value": "6"
        }
      ],
      "date_start": "2026-03-17",
      "date_stop": "2026-03-24"
    },
    {
      "campaign_name": "Jídelní_Židle+kresilka_broad_Video_V1",
      "adset_name": "Broad_30-60_Jídelní_kresilka_Video_V1",
      "ad_name": "Jídelní_Křesílka_V3",
      "impressions": "332",
      "clicks": "12",
      "spend": "50.21",
      "ctr": "3.614458",
      "cpc": "4.184167",
      "actions": [
        {
          "action_type": "link_click",
          "value": "7"
        },
        {
          "action_type": "page_engagement",
          "value": "82"
        },
        {
          "action_type": "landing_page_view",
          "value": "7"
        },
        {
          "action_type": "omni_landing_page_view",
          "value": "7"
        },
        {
          "action_type": "onsite_web_view_content",
          "value": "4"
        },
        {
          "action_type": "post_interaction_gross",
          "value": "1"
        },
        {
          "action_type": "onsite_web_app_view_content",
          "value": "4"
        },
        {
          "action_type": "view_content",
          "value": "4"
        },
        {
          "action_type": "onsite_conversion.post_save",
          "value": "1"
        },
        {
          "action_type": "post_engagement",
          "value": "82"
        },
        {
          "action_type": "onsite_conversion.post_net_save",
          "value": "1"
        },
        {
          "action_type": "offsite_content_view_add_meta_leads",
          "value": "4"
        },
        {
          "action_type": "video_view",
          "value": "74"
        },
        {
          "action_type": "omni_view_content",
          "value": "4"
        },
        {
          "action_type": "offsite_conversion.fb_pixel_view_content",
          "value": "4"
        }
      ],
      "date_start": "2026-03-17",
      "date_stop": "2026-03-24"
    },
    {
      "campaign_name": "Výprodeje",
      "adset_name": "Broad_výprodej_green, aida, manta",
      "ad_name": "Akce-výprodej-green",
      "impressions": "12845",
      "clicks": "94",
      "spend": "1349.89",
      "ctr": "0.731802",
      "cpc": "14.360532",
      "actions": [
        {
          "action_type": "omni_search",
          "value": "2"
        },
        {
          "action_type": "offsite_conversion.fb_pixel_search",
          "value": "2"
        },
        {
          "action_type": "link_click",
          "value": "82"
        },
        {
          "action_type": "omni_add_to_cart",
          "value": "1"
        },
        {
          "action_type": "omni_initiated_checkout",
          "value": "5"
        },
        {
          "action_type": "page_engagement",
          "value": "85"
        },
        {
          "action_type": "landing_page_view",
          "value": "64"
        },
        {
          "action_type": "add_to_cart",
          "value": "1"
        },
        {
          "action_type": "omni_landing_page_view",
          "value": "64"
        },
        {
          "action_type": "onsite_web_view_content",
          "value": "91"
        },
        {
          "action_type": "onsite_web_add_to_cart",
          "value": "1"
        },
        {
          "action_type": "offsite_conversion.fb_pixel_add_payment_info",
          "value": "5"
        },
        {
          "action_type": "like",
          "value": "1"
        },
        {
          "action_type": "post_interaction_gross",
          "value": "2"
        },
        {
          "action_type": "onsite_web_app_view_content",
          "value": "91"
        },
        {
          "action_type": "view_content",
          "value": "91"
        },
        {
          "action_type": "onsite_web_app_add_to_cart",
          "value": "1"
        },
        {
          "action_type": "post_engagement",
          "value": "84"
        },
        {
          "action_type": "offsite_search_add_meta_leads",
          "value": "2"
        },
        {
          "action_type": "onsite_conversion.post_net_like",
          "value": "2"
        },
        {
          "action_type": "onsite_web_initiate_checkout",
          "value": "5"
        },
        {
          "action_type": "offsite_content_view_add_meta_leads",
          "value": "91"
        },
        {
          "action_type": "add_payment_info",
          "value": "5"
        },
        {
          "action_type": "search",
          "value": "2"
        },
        {
          "action_type": "omni_view_content",
          "value": "91"
        },
        {
          "action_type": "offsite_conversion.fb_pixel_view_content",
          "value": "91"
        },
        {
          "action_type": "offsite_conversion.fb_pixel_add_to_cart",
          "value": "1"
        },
        {
          "action_type": "post_reaction",
          "value": "2"
        },
        {
          "action_type": "offsite_conversion.fb_pixel_initiate_checkout",
          "value": "5"
        },
        {
          "action_type": "initiate_checkout",
          "value": "5"
        }
      ],
      "date_start": "2026-03-17",
      "date_stop": "2026-03-24"
    },
    {
      "campaign_name": "Výprodeje",
      "adset_name": "Broad_Akce_Leden",
      "ad_name": "Akce_leden",
      "impressions": "1795",
      "clicks": "23",
      "spend": "195.55",
      "ctr": "1.281337",
      "cpc": "8.502174",
      "actions": [
        {
          "action_type": "web_in_store_purchase",
          "value": "1"
        },
        {
          "action_type": "omni_purchase",
          "value": "1"
        },
        {
          "action_type": "link_click",
          "value": "17"
        },
        {
          "action_type": "omni_add_to_cart",
          "value": "2"
        },
        {
          "action_type": "omni_initiated_checkout",
          "value": "2"
        },
        {
          "action_type": "page_engagement",
          "value": "17"
        },
        {
          "action_type": "purchase",
          "value": "1"
        },
        {
          "action_type": "landing_page_view",
          "value": "10"
        },
        {
          "action_type": "add_to_cart",
          "value": "2"
        },
        {
          "action_type": "omni_landing_page_view",
          "value": "10"
        },
        {
          "action_type": "onsite_web_view_content",
          "value": "26"
        },
        {
          "action_type": "onsite_web_add_to_cart",
          "value": "2"
        },
        {
          "action_type": "offsite_conversion.fb_pixel_add_payment_info",
          "value": "1"
        },
        {
          "action_type": "onsite_web_app_purchase",
          "value": "1"
        },
        {
          "action_type": "offsite_conversion.fb_pixel_purchase",
          "value": "1"
        },
        {
          "action_type": "onsite_web_app_view_content",
          "value": "26"
        },
        {
          "action_type": "view_content",
          "value": "26"
        },
        {
          "action_type": "web_app_in_store_purchase",
          "value": "1"
        },
        {
          "action_type": "onsite_web_app_add_to_cart",
          "value": "2"
        },
        {
          "action_type": "post_engagement",
          "value": "17"
        },
        {
          "action_type": "onsite_web_initiate_checkout",
          "value": "2"
        },
        {
          "action_type": "offsite_content_view_add_meta_leads",
          "value": "26"
        },
        {
          "action_type": "onsite_web_purchase",
          "value": "1"
        },
        {
          "action_type": "add_payment_info",
          "value": "1"
        },
        {
          "action_type": "omni_view_content",
          "value": "26"
        },
        {
          "action_type": "offsite_conversion.fb_pixel_view_content",
          "value": "26"
        },
        {
          "action_type": "offsite_conversion.fb_pixel_add_to_cart",
          "value": "2"
        },
        {
          "action_type": "offsite_conversion.fb_pixel_initiate_checkout",
          "value": "2"
        },
        {
          "action_type": "initiate_checkout",
          "value": "2"
        }
      ],
      "date_start": "2026-03-17",
      "date_stop": "2026-03-24"
    },
    {
      "campaign_name": "Výprodeje",
      "adset_name": "Broad_AKCE_NARDI_Brezen",
      "ad_name": "Nardi_kod",
      "impressions": "12152",
      "clicks": "144",
      "spend": "1386.95",
      "ctr": "1.18499",
      "cpc": "9.631597",
      "actions": [
        {
          "action_type": "web_in_store_purchase",
          "value": "1"
        },
        {
          "action_type": "omni_purchase",
          "value": "1"
        },
        {
          "action_type": "link_click",
          "value": "131"
        },
        {
          "action_type": "omni_add_to_cart",
          "value": "5"
        },
        {
          "action_type": "omni_initiated_checkout",
          "value": "4"
        },
        {
          "action_type": "page_engagement",
          "value": "132"
        },
        {
          "action_type": "purchase",
          "value": "1"
        },
        {
          "action_type": "landing_page_view",
          "value": "109"
        },
        {
          "action_type": "add_to_cart",
          "value": "5"
        },
        {
          "action_type": "omni_landing_page_view",
          "value": "109"
        },
        {
          "action_type": "onsite_web_view_content",
          "value": "53"
        },
        {
          "action_type": "onsite_web_add_to_cart",
          "value": "5"
        },
        {
          "action_type": "onsite_web_app_purchase",
          "value": "1"
        },
        {
          "action_type": "post_interaction_gross",
          "value": "1"
        },
        {
          "action_type": "offsite_conversion.fb_pixel_purchase",
          "value": "1"
        },
        {
          "action_type": "onsite_web_app_view_content",
          "value": "53"
        },
        {
          "action_type": "view_content",
          "value": "53"
        },
        {
          "action_type": "web_app_in_store_purchase",
          "value": "1"
        },
        {
          "action_type": "onsite_web_app_add_to_cart",
          "value": "5"
        },
        {
          "action_type": "post_engagement",
          "value": "132"
        },
        {
          "action_type": "onsite_conversion.post_net_like",
          "value": "1"
        },
        {
          "action_type": "onsite_web_initiate_checkout",
          "value": "4"
        },
        {
          "action_type": "offsite_content_view_add_meta_leads",
          "value": "53"
        },
        {
          "action_type": "onsite_web_purchase",
          "value": "1"
        },
        {
          "action_type": "omni_view_content",
          "value": "53"
        },
        {
          "action_type": "offsite_conversion.fb_pixel_view_content",
          "value": "53"
        },
        {
          "action_type": "offsite_conversion.fb_pixel_add_to_cart",
          "value": "5"
        },
        {
          "action_type": "post_reaction",
          "value": "1"
        },
        {
          "action_type": "offsite_conversion.fb_pixel_initiate_checkout",
          "value": "4"
        },
        {
          "action_type": "initiate_checkout",
          "value": "4"
        }
      ],
      "date_start": "2026-03-17",
      "date_stop": "2026-03-24"
    }
  ],
  "paging": {
    "cursors": {
      "before": "MAZDZD",
      "after": "MTIZD"
    }
  },
  "fetched_at": "2026-03-24T05:57:04.097372",
  "account": "Zidlestoly.cz",
  "period": {
    "since": "2026-03-17",
    "until": "2026-03-24"
  }
}